LICENSE.txt
MANIFEST.in
README.rst
setup.cfg
setup.py
bin/sudden
data/data_file
sudden/__init__.py
sudden/main.py
sudden.egg-info/PKG-INFO
sudden.egg-info/SOURCES.txt
sudden.egg-info/dependency_links.txt
sudden.egg-info/entry_points.txt
sudden.egg-info/requires.txt
sudden.egg-info/top_level.txt