Metadata-Version: 1.1
Name: sudden
Version: 0.0.1
Summary: A sudden automation tool for installing software in Ubuntu/Debian systems
Home-page: https://github.com/raonyguimaraes/sudden
Author: Raony Guimaraes
Author-email: raonyguimaraes@gmail.com
License: BSD-3
Keywords: sudden setuptools development
Platform: UNKNOWN
Classifier: Development Status :: 3 - Alpha
Classifier: Intended Audience :: Developers
Classifier: Topic :: Software Development :: Build Tools
Classifier: Programming Language :: Python :: 2
Classifier: Programming Language :: Python :: 2.7
Classifier: Programming Language :: Python :: 3
Classifier: Programming Language :: Python :: 3.3
Classifier: Programming Language :: Python :: 3.4
Classifier: Programming Language :: Python :: 3.5
Classifier: Programming Language :: Python :: 3.6
